{"total":18,"serverTime":1761087255757,"videoList":[{"num":1,"video_id":"VIDEnlQo78rmAzVcwQco1iuK110723","video_title":"[视频]温家宝就挪威爆炸和枪击事件向挪威首相致慰问电","video_image":"https://p3.img.cctvpic.com/fmspic/2011/07/23/32be20696e4a461a6a95c3b88ab6566a-1.jpg","guid":"32be20696e4a461a6a95c3b88ab6566a","video_length":"00:00:18","video_tag":"","video_url":"https://tv.cctv.com/2011/07/23/VIDEnlQo78rmAzVcwQco1iuK110723.shtml","page_id":"PAGE4y8I53JvSWE8DlRSMlbu160121","edit_mode":"1","brief":"","pub_date":"2011-07-23 18:59:56","news_hl_tag":"","video_detail":{"id":"VIDEnlQo78rmAzVcwQco1iuK110723","guid":"32be20696e4a461a6a95c3b88ab6566a","title":"[视频]温家宝就挪威爆炸和枪击事件向挪威首相致慰问电","source":"央视网","pubtime":"2011-07-23 18:59:56","content":"","logo":"https://p3.img.cctvpic.com/fmspic/2011/07/23/32be20696e4a461a6a95c3b88ab6566a-1.jpg","url":"https://tv.cctv.com/2011/07/23/VIDEnlQo78rmAzVcwQco1iuK110723.shtml","catalog":"","allow_share":"1","allow_praise":"1","allow_comment":"1","channel_id":"CHAL1450952056131267","topic_id":"TOPC1451528971114112","primary_page_id":"PAGE4y8I53JvSWE8DlRSMlbu160121","desc":"","brief":"","tag":""}},{"num":2,"video_id":"VIDEqjJF7ha0vAtYdN4sHmsH110723","video_title":"[视频]挪威接连发生爆炸枪击事件 90多人死亡","video_image":"https://p2.img.cctvpic.com/fmspic/2011/07/23/31ffa2dd00bc4980e8d7eca3bfc3f9a1-1.jpg","guid":"31ffa2dd00bc4980e8d7eca3bfc3f9a1","video_length":"00:02:19","video_tag":"","video_url":"https://tv.cctv.com/2011/07/23/VIDEqjJF7ha0vAtYdN4sHmsH110723.shtml","page_id":"PAGE4y8I53JvSWE8DlRSMlbu160121","edit_mode":"1","brief":"","pub_date":"2011-07-23 19:03:02","news_hl_tag":"","video_detail":{"id":"VIDEqjJF7ha0vAtYdN4sHmsH110723","guid":"31ffa2dd00bc4980e8d7eca3bfc3f9a1","title":"[视频]挪威接连发生爆炸枪击事件 90多人死亡","source":"央视网","pubtime":"2011-07-23 19:03:02","content":"","logo":"https://p2.img.cctvpic.com/fmspic/2011/07/23/31ffa2dd00bc4980e8d7eca3bfc3f9a1-1.jpg","url":"https://tv.cctv.com/2011/07/23/VIDEqjJF7ha0vAtYdN4sHmsH110723.shtml","catalog":"","allow_share":"1","allow_praise":"1","allow_comment":"1","channel_id":"CHAL1450952056131267","topic_id":"TOPC1451528971114112","primary_page_id":"PAGE4y8I53JvSWE8DlRSMlbu160121","desc":"","brief":"","tag":""}},{"num":3,"video_id":"VIDEigHHhQLVSr2t5uL5Q0fN110723","video_title":"[视频]贵州：产业园区凸显集聚效应 工业经济稳步“爬高”","video_image":"https://p4.img.cctvpic.com/fmspic/2011/07/23/d7e0166f14a04b9acae5b0b7f4b46d16-1.jpg","guid":"d7e0166f14a04b9acae5b0b7f4b46d16","video_length":"00:01:57","video_tag":"","video_url":"https://tv.cctv.com/2011/07/23/VIDEigHHhQLVSr2t5uL5Q0fN110723.shtml","page_id":"PAGE4y8I53JvSWE8DlRSMlbu160121","edit_mode":"1","brief":"","pub_date":"2011-07-23 19:04:50","news_hl_tag":"","video_detail":{"id":"VIDEigHHhQLVSr2t5uL5Q0fN110723","guid":"d7e0166f14a04b9acae5b0b7f4b46d16","title":"[视频]贵州：产业园区凸显集聚效应 工业经济稳步“爬高”","source":"央视网","pubtime":"2011-07-23 19:04:50","content":"","logo":"https://p4.img.cctvpic.com/fmspic/2011/07/23/d7e0166f14a04b9acae5b0b7f4b46d16-1.jpg","url":"https://tv.cctv.com/2011/07/23/VIDEigHHhQLVSr2t5uL5Q0fN110723.shtml","catalog":"","allow_share":"1","allow_praise":"1","allow_comment":"1","channel_id":"CHAL1450952056131267","topic_id":"TOPC1451528971114112","primary_page_id":"PAGE4y8I53JvSWE8DlRSMlbu160121","desc":"","brief":"","tag":""}},{"num":4,"video_id":"VIDE6SdNVtDRIvaoPLK99jSF110723","video_title":"[视频]〖保障性住房建设巡礼〗浙江：广纳社会资本 加快保障房建设","video_image":"https://p1.img.cctvpic.com/fmspic/2011/07/23/865c88b0f7724191ce6a17be9ea19276-1.jpg","guid":"865c88b0f7724191ce6a17be9ea19276","video_length":"00:02:06","video_tag":"","video_url":"https://tv.cctv.com/2011/07/23/VIDE6SdNVtDRIvaoPLK99jSF110723.shtml","page_id":"PAGE4y8I53JvSWE8DlRSMlbu160121","edit_mode":"1","brief":"","pub_date":"2011-07-23 19:05:53","news_hl_tag":"","video_detail":{"id":"VIDE6SdNVtDRIvaoPLK99jSF110723","guid":"865c88b0f7724191ce6a17be9ea19276","title":"[视频]〖保障性住房建设巡礼〗浙江：广纳社会资本 加快保障房建设","source":"央视网","pubtime":"2011-07-23 19:05:53","content":"","logo":"https://p1.img.cctvpic.com/fmspic/2011/07/23/865c88b0f7724191ce6a17be9ea19276-1.jpg","url":"https://tv.cctv.com/2011/07/23/VIDE6SdNVtDRIvaoPLK99jSF110723.shtml","catalog":"","allow_share":"1","allow_praise":"1","allow_comment":"1","channel_id":"CHAL1450952056131267","topic_id":"TOPC1451528971114112","primary_page_id":"PAGE4y8I53JvSWE8DlRSMlbu160121","desc":"","brief":"","tag":""}},{"num":5,"video_id":"VIDEzNmD4WxAn45L8iKx6bsD110723","video_title":"[视频]全国道德模范与身边好人现场交流活动在内蒙古 江苏进行","video_image":"https://p4.img.cctvpic.com/fmspic/2011/07/23/6664f7764e5b434af087d6bc02460095-1.jpg","guid":"6664f7764e5b434af087d6bc02460095","video_length":"00:00:39","video_tag":"","video_url":"https://tv.cctv.com/2011/07/23/VIDEzNmD4WxAn45L8iKx6bsD110723.shtml","page_id":"PAGE4y8I53JvSWE8DlRSMlbu160121","edit_mode":"1","brief":"","pub_date":"2011-07-23 19:08:20","news_hl_tag":"","video_detail":{"id":"VIDEzNmD4WxAn45L8iKx6bsD110723","guid":"6664f7764e5b434af087d6bc02460095","title":"[视频]全国道德模范与身边好人现场交流活动在内蒙古 江苏进行","source":"央视网","pubtime":"2011-07-23 19:08:20","content":"","logo":"https://p4.img.cctvpic.com/fmspic/2011/07/23/6664f7764e5b434af087d6bc02460095-1.jpg","url":"https://tv.cctv.com/2011/07/23/VIDEzNmD4WxAn45L8iKx6bsD110723.shtml","catalog":"","allow_share":"1","allow_praise":"1","allow_comment":"1","channel_id":"CHAL1450952056131267","topic_id":"TOPC1451528971114112","primary_page_id":"PAGE4y8I53JvSWE8DlRSMlbu160121","desc":"","brief":"","tag":""}},{"num":6,"video_id":"VIDEqqvIt43pe2QT9qvZsaXi110723","video_title":"[视频]新疆哈密：主题教育方式多 聚合民心促发展","video_image":"https://p3.img.cctvpic.com/fmspic/2011/07/23/cf1d361d80fd4895cc0f70bd3c70cb95-1.jpg","guid":"cf1d361d80fd4895cc0f70bd3c70cb95","video_length":"00:01:01","video_tag":"","video_url":"https://tv.cctv.com/2011/07/23/VIDEqqvIt43pe2QT9qvZsaXi110723.shtml","page_id":"PAGE4y8I53JvSWE8DlRSMlbu160121","edit_mode":"1","brief":"","pub_date":"2011-07-23 19:09:49","news_hl_tag":"","video_detail":{"id":"VIDEqqvIt43pe2QT9qvZsaXi110723","guid":"cf1d361d80fd4895cc0f70bd3c70cb95","title":"[视频]新疆哈密：主题教育方式多 聚合民心促发展","source":"央视网","pubtime":"2011-07-23 19:09:49","content":"","logo":"https://p3.img.cctvpic.com/fmspic/2011/07/23/cf1d361d80fd4895cc0f70bd3c70cb95-1.jpg","url":"https://tv.cctv.com/2011/07/23/VIDEqqvIt43pe2QT9qvZsaXi110723.shtml","catalog":"","allow_share":"1","allow_praise":"1","allow_comment":"1","channel_id":"CHAL1450952056131267","topic_id":"TOPC1451528971114112","primary_page_id":"PAGE4y8I53JvSWE8DlRSMlbu160121","desc":"","brief":"","tag":""}},{"num":7,"video_id":"VIDEj9kllMsUjjCDdjxkcMsq110723","video_title":"[视频]河北石家庄：建设民生城市 提升市民幸福感","video_image":"https://p2.img.cctvpic.com/fmspic/2011/07/23/674a0af5b8dc40943f789a8444fb3ad5-1.jpg","guid":"674a0af5b8dc40943f789a8444fb3ad5","video_length":"00:01:31","video_tag":"","video_url":"https://tv.cctv.com/2011/07/23/VIDEj9kllMsUjjCDdjxkcMsq110723.shtml","page_id":"PAGE4y8I53JvSWE8DlRSMlbu160121","edit_mode":"1","brief":"","pub_date":"2011-07-23 19:12:56","news_hl_tag":"","video_detail":{"id":"VIDEj9kllMsUjjCDdjxkcMsq110723","guid":"674a0af5b8dc40943f789a8444fb3ad5","title":"[视频]河北石家庄：建设民生城市 提升市民幸福感","source":"央视网","pubtime":"2011-07-23 19:12:56","content":"","logo":"https://p2.img.cctvpic.com/fmspic/2011/07/23/674a0af5b8dc40943f789a8444fb3ad5-1.jpg","url":"https://tv.cctv.com/2011/07/23/VIDEj9kllMsUjjCDdjxkcMsq110723.shtml","catalog":"","allow_share":"1","allow_praise":"1","allow_comment":"1","channel_id":"CHAL1450952056131267","topic_id":"TOPC1451528971114112","primary_page_id":"PAGE4y8I53JvSWE8DlRSMlbu160121","desc":"","brief":"","tag":""}},{"num":8,"video_id":"VIDEXWSWnKgqftF2D7RUCeM3110723","video_title":"[视频]江苏海门：创建拥军新模式","video_image":"https://p4.img.cctvpic.com/fmspic/2011/07/23/c37df882daed43cabb457dba4888383b-1.jpg","guid":"c37df882daed43cabb457dba4888383b","video_length":"00:01:23","video_tag":"","video_url":"https://tv.cctv.com/2011/07/23/VIDEXWSWnKgqftF2D7RUCeM3110723.shtml","page_id":"PAGE4y8I53JvSWE8DlRSMlbu160121","edit_mode":"1","brief":"","pub_date":"2011-07-23 19:13:04","news_hl_tag":"","video_detail":{"id":"VIDEXWSWnKgqftF2D7RUCeM3110723","guid":"c37df882daed43cabb457dba4888383b","title":"[视频]江苏海门：创建拥军新模式","source":"央视网","pubtime":"2011-07-23 19:13:04","content":"","logo":"https://p4.img.cctvpic.com/fmspic/2011/07/23/c37df882daed43cabb457dba4888383b-1.jpg","url":"https://tv.cctv.com/2011/07/23/VIDEXWSWnKgqftF2D7RUCeM3110723.shtml","catalog":"","allow_share":"1","allow_praise":"1","allow_comment":"1","channel_id":"CHAL1450952056131267","topic_id":"TOPC1451528971114112","primary_page_id":"PAGE4y8I53JvSWE8DlRSMlbu160121","desc":"","brief":"","tag":""}},{"num":9,"video_id":"VIDEdy1WkaNfwno3PGX35pqd110723","video_title":"[视频]甘肃省杂技团：积极开拓市场 发掘文化新价值","video_image":"https://p3.img.cctvpic.com/fmspic/2011/07/23/76ced60846df4af9b098d8b5689e0b15-1.jpg","guid":"76ced60846df4af9b098d8b5689e0b15","video_length":"00:01:36","video_tag":"","video_url":"https://tv.cctv.com/2011/07/23/VIDEdy1WkaNfwno3PGX35pqd110723.shtml","page_id":"PAGE4y8I53JvSWE8DlRSMlbu160121","edit_mode":"1","brief":"","pub_date":"2011-07-23 19:15:59","news_hl_tag":"","video_detail":{"id":"VIDEdy1WkaNfwno3PGX35pqd110723","guid":"76ced60846df4af9b098d8b5689e0b15","title":"[视频]甘肃省杂技团：积极开拓市场 发掘文化新价值","source":"央视网","pubtime":"2011-07-23 19:15:59","content":"","logo":"https://p3.img.cctvpic.com/fmspic/2011/07/23/76ced60846df4af9b098d8b5689e0b15-1.jpg","url":"https://tv.cctv.com/2011/07/23/VIDEdy1WkaNfwno3PGX35pqd110723.shtml","catalog":"","allow_share":"1","allow_praise":"1","allow_comment":"1","channel_id":"CHAL1450952056131267","topic_id":"TOPC1451528971114112","primary_page_id":"PAGE4y8I53JvSWE8DlRSMlbu160121","desc":"","brief":"","tag":""}},{"num":10,"video_id":"VIDEgY40oflQ3hQjYoYWG2vC110723","video_title":"[视频]发射天宫一号的运载火箭运抵载人航天发射场","video_image":"https://p4.img.cctvpic.com/fmspic/2011/07/23/7ca91e1d7c2d4d504ce316aa09836615-1.jpg","guid":"7ca91e1d7c2d4d504ce316aa09836615","video_length":"00:01:07","video_tag":"","video_url":"https://tv.cctv.com/2011/07/23/VIDEgY40oflQ3hQjYoYWG2vC110723.shtml","page_id":"PAGE4y8I53JvSWE8DlRSMlbu160121","edit_mode":"1","brief":"","pub_date":"2011-07-23 19:16:12","news_hl_tag":"","video_detail":{"id":"VIDEgY40oflQ3hQjYoYWG2vC110723","guid":"7ca91e1d7c2d4d504ce316aa09836615","title":"[视频]发射天宫一号的运载火箭运抵载人航天发射场","source":"央视网","pubtime":"2011-07-23 19:16:12","content":"","logo":"https://p4.img.cctvpic.com/fmspic/2011/07/23/7ca91e1d7c2d4d504ce316aa09836615-1.jpg","url":"https://tv.cctv.com/2011/07/23/VIDEgY40oflQ3hQjYoYWG2vC110723.shtml","catalog":"","allow_share":"1","allow_praise":"1","allow_comment":"1","channel_id":"CHAL1450952056131267","topic_id":"TOPC1451528971114112","primary_page_id":"PAGE4y8I53JvSWE8DlRSMlbu160121","desc":"","brief":"","tag":""}},{"num":11,"video_id":"VIDE0G2t0vPhyz2pvVxrIvQ7110723","video_title":"[视频]中国夺取跳水第九金 花游姊妹花获亚军","video_image":"https://p4.img.cctvpic.com/fmspic/2011/07/23/270473f564cf48755307f0a44c25fb6d-1.jpg","guid":"270473f564cf48755307f0a44c25fb6d","video_length":"00:01:00","video_tag":"","video_url":"https://tv.cctv.com/2011/07/23/VIDE0G2t0vPhyz2pvVxrIvQ7110723.shtml","page_id":"PAGE4y8I53JvSWE8DlRSMlbu160121","edit_mode":"1","brief":"","pub_date":"2011-07-23 19:17:43","news_hl_tag":"","video_detail":{"id":"VIDE0G2t0vPhyz2pvVxrIvQ7110723","guid":"270473f564cf48755307f0a44c25fb6d","title":"[视频]中国夺取跳水第九金 花游姊妹花获亚军","source":"央视网","pubtime":"2011-07-23 19:17:43","content":"","logo":"https://p4.img.cctvpic.com/fmspic/2011/07/23/270473f564cf48755307f0a44c25fb6d-1.jpg","url":"https://tv.cctv.com/2011/07/23/VIDE0G2t0vPhyz2pvVxrIvQ7110723.shtml","catalog":"","allow_share":"1","allow_praise":"1","allow_comment":"1","channel_id":"CHAL1450952056131267","topic_id":"TOPC1451528971114112","primary_page_id":"PAGE4y8I53JvSWE8DlRSMlbu160121","desc":"","brief":"","tag":""}},{"num":12,"video_id":"VIDEsqRJtWmbrchVzgocwDMs110723","video_title":"[视频]“大暑”节气 高温暴雨轮番登场","video_image":"https://p4.img.cctvpic.com/fmspic/2011/07/23/006d5a6cb2b84b012fc32e92d6dc4fe2-1.jpg","guid":"006d5a6cb2b84b012fc32e92d6dc4fe2","video_length":"00:00:59","video_tag":"","video_url":"https://tv.cctv.com/2011/07/23/VIDEsqRJtWmbrchVzgocwDMs110723.shtml","page_id":"PAGE4y8I53JvSWE8DlRSMlbu160121","edit_mode":"1","brief":"","pub_date":"2011-07-23 19:17:59","news_hl_tag":"","video_detail":{"id":"VIDEsqRJtWmbrchVzgocwDMs110723","guid":"006d5a6cb2b84b012fc32e92d6dc4fe2","title":"[视频]“大暑”节气 高温暴雨轮番登场","source":"央视网","pubtime":"2011-07-23 19:17:59","content":"","logo":"https://p4.img.cctvpic.com/fmspic/2011/07/23/006d5a6cb2b84b012fc32e92d6dc4fe2-1.jpg","url":"https://tv.cctv.com/2011/07/23/VIDEsqRJtWmbrchVzgocwDMs110723.shtml","catalog":"","allow_share":"1","allow_praise":"1","allow_comment":"1","channel_id":"CHAL1450952056131267","topic_id":"TOPC1451528971114112","primary_page_id":"PAGE4y8I53JvSWE8DlRSMlbu160121","desc":"","brief":"","tag":""}},{"num":13,"video_id":"VIDEdCJmADIlRKQ2oLX7b70Y110723","video_title":"[视频]首批藏羚羊到达楚玛尔河河畔 寻找时机过河","video_image":"https://p2.img.cctvpic.com/fmspic/2011/07/23/7fcc3fdec4034469e3f2ddb11febd5a7-1.jpg","guid":"7fcc3fdec4034469e3f2ddb11febd5a7","video_length":"00:01:20","video_tag":"","video_url":"https://tv.cctv.com/2011/07/23/VIDEdCJmADIlRKQ2oLX7b70Y110723.shtml","page_id":"PAGE4y8I53JvSWE8DlRSMlbu160121","edit_mode":"1","brief":"","pub_date":"2011-07-23 19:19:13","news_hl_tag":"","video_detail":{"id":"VIDEdCJmADIlRKQ2oLX7b70Y110723","guid":"7fcc3fdec4034469e3f2ddb11febd5a7","title":"[视频]首批藏羚羊到达楚玛尔河河畔 寻找时机过河","source":"央视网","pubtime":"2011-07-23 19:19:13","content":"","logo":"https://p2.img.cctvpic.com/fmspic/2011/07/23/7fcc3fdec4034469e3f2ddb11febd5a7-1.jpg","url":"https://tv.cctv.com/2011/07/23/VIDEdCJmADIlRKQ2oLX7b70Y110723.shtml","catalog":"","allow_share":"1","allow_praise":"1","allow_comment":"1","channel_id":"CHAL1450952056131267","topic_id":"TOPC1451528971114112","primary_page_id":"PAGE4y8I53JvSWE8DlRSMlbu160121","desc":"","brief":"","tag":""}},{"num":14,"video_id":"VIDETwJtI6XllIdQu9feUb9g110723","video_title":"[视频]电视剧《中国地》今晚播出","video_image":"https://p5.img.cctvpic.com/fmspic/2011/07/23/aadc39ec4abc40d09b3f1ab3dab4daf7-1.jpg","guid":"aadc39ec4abc40d09b3f1ab3dab4daf7","video_length":"00:00:19","video_tag":"","video_url":"https://tv.cctv.com/2011/07/23/VIDETwJtI6XllIdQu9feUb9g110723.shtml","page_id":"PAGE4y8I53JvSWE8DlRSMlbu160121","edit_mode":"1","brief":"","pub_date":"2011-07-23 19:19:40","news_hl_tag":"","video_detail":{"id":"VIDETwJtI6XllIdQu9feUb9g110723","guid":"aadc39ec4abc40d09b3f1ab3dab4daf7","title":"[视频]电视剧《中国地》今晚播出","source":"央视网","pubtime":"2011-07-23 19:19:40","content":"","logo":"https://p5.img.cctvpic.com/fmspic/2011/07/23/aadc39ec4abc40d09b3f1ab3dab4daf7-1.jpg","url":"https://tv.cctv.com/2011/07/23/VIDETwJtI6XllIdQu9feUb9g110723.shtml","catalog":"","allow_share":"1","allow_praise":"1","allow_comment":"1","channel_id":"CHAL1450952056131267","topic_id":"TOPC1451528971114112","primary_page_id":"PAGE4y8I53JvSWE8DlRSMlbu160121","desc":"","brief":"","tag":""}},{"num":15,"video_id":"VIDEZpkTgmDFreTObrMpzssN110723","video_title":"[视频]国内简讯","video_image":"https://p2.img.cctvpic.com/fmspic/2011/07/23/5e4c80ee4ab24c54d4b6cba3ba167c65-1.jpg","guid":"5e4c80ee4ab24c54d4b6cba3ba167c65","video_length":"00:01:08","video_tag":"","video_url":"https://tv.cctv.com/2011/07/23/VIDEZpkTgmDFreTObrMpzssN110723.shtml","page_id":"PAGE4y8I53JvSWE8DlRSMlbu160121","edit_mode":"1","brief":"","pub_date":"2011-07-23 19:20:45","news_hl_tag":"","video_detail":{"id":"VIDEZpkTgmDFreTObrMpzssN110723","guid":"5e4c80ee4ab24c54d4b6cba3ba167c65","title":"[视频]国内简讯","source":"央视网","pubtime":"2011-07-23 19:20:45","content":"","logo":"https://p2.img.cctvpic.com/fmspic/2011/07/23/5e4c80ee4ab24c54d4b6cba3ba167c65-1.jpg","url":"https://tv.cctv.com/2011/07/23/VIDEZpkTgmDFreTObrMpzssN110723.shtml","catalog":"","allow_share":"1","allow_praise":"1","allow_comment":"1","channel_id":"CHAL1450952056131267","topic_id":"TOPC1451528971114112","primary_page_id":"PAGE4y8I53JvSWE8DlRSMlbu160121","desc":"","brief":"","tag":""}},{"num":16,"video_id":"VIDEJDYJkrRf9Qey1j7PyjJ4110723","video_title":"[视频]杨洁篪出席东亚峰会外长磋商及第18届东盟地区论坛外长会","video_image":"https://p5.img.cctvpic.com/fmspic/2011/07/23/f976f746736644b71034dea4ee4b1a30-1.jpg","guid":"f976f746736644b71034dea4ee4b1a30","video_length":"00:00:44","video_tag":"","video_url":"https://tv.cctv.com/2011/07/23/VIDEJDYJkrRf9Qey1j7PyjJ4110723.shtml","page_id":"PAGE4y8I53JvSWE8DlRSMlbu160121","edit_mode":"1","brief":"","pub_date":"2011-07-23 19:21:09","news_hl_tag":"","video_detail":{"id":"VIDEJDYJkrRf9Qey1j7PyjJ4110723","guid":"f976f746736644b71034dea4ee4b1a30","title":"[视频]杨洁篪出席东亚峰会外长磋商及第18届东盟地区论坛外长会","source":"央视网","pubtime":"2011-07-23 19:21:09","content":"","logo":"https://p5.img.cctvpic.com/fmspic/2011/07/23/f976f746736644b71034dea4ee4b1a30-1.jpg","url":"https://tv.cctv.com/2011/07/23/VIDEJDYJkrRf9Qey1j7PyjJ4110723.shtml","catalog":"","allow_share":"1","allow_praise":"1","allow_comment":"1","channel_id":"CHAL1450952056131267","topic_id":"TOPC1451528971114112","primary_page_id":"PAGE4y8I53JvSWE8DlRSMlbu160121","desc":"","brief":"","tag":""}},{"num":17,"video_id":"VIDEg25vh459PRSXlblbF4Pe110723","video_title":"[视频]美国：众议长暂退出谈判 债务谈判仍陷僵局","video_image":"https://p4.img.cctvpic.com/fmspic/2011/07/23/9619045fa2a4444c4a2284926baf95c0-1.jpg","guid":"9619045fa2a4444c4a2284926baf95c0","video_length":"00:01:16","video_tag":"","video_url":"https://tv.cctv.com/2011/07/23/VIDEg25vh459PRSXlblbF4Pe110723.shtml","page_id":"PAGE4y8I53JvSWE8DlRSMlbu160121","edit_mode":"1","brief":"","pub_date":"2011-07-23 19:22:14","news_hl_tag":"国际资讯","video_detail":{"id":"VIDEg25vh459PRSXlblbF4Pe110723","guid":"9619045fa2a4444c4a2284926baf95c0","title":"[视频]美国：众议长暂退出谈判 债务谈判仍陷僵局","source":"央视网","pubtime":"2011-07-23 19:22:14","content":"","logo":"https://p4.img.cctvpic.com/fmspic/2011/07/23/9619045fa2a4444c4a2284926baf95c0-1.jpg","url":"https://tv.cctv.com/2011/07/23/VIDEg25vh459PRSXlblbF4Pe110723.shtml","catalog":"","allow_share":"1","allow_praise":"1","allow_comment":"1","channel_id":"CHAL1450952056131267","topic_id":"TOPC1451528971114112","primary_page_id":"PAGE4y8I53JvSWE8DlRSMlbu160121","desc":"","brief":"","tag":""}},{"num":18,"video_id":"VIDEA0BVwHIUe77gElK1TNFS110723","video_title":"[视频]国际简讯","video_image":"https://p5.img.cctvpic.com/fmspic/2011/07/23/f1412bc4924c4b51d796e09391f2baeb-1.jpg","guid":"f1412bc4924c4b51d796e09391f2baeb","video_length":"00:01:47","video_tag":"","video_url":"https://tv.cctv.com/2011/07/23/VIDEA0BVwHIUe77gElK1TNFS110723.shtml","page_id":"PAGE4y8I53JvSWE8DlRSMlbu160121","edit_mode":"1","brief":"","pub_date":"2011-07-23 19:24:40","news_hl_tag":"","video_detail":{"id":"VIDEA0BVwHIUe77gElK1TNFS110723","guid":"f1412bc4924c4b51d796e09391f2baeb","title":"[视频]国际简讯","source":"央视网","pubtime":"2011-07-23 19:24:40","content":"","logo":"https://p5.img.cctvpic.com/fmspic/2011/07/23/f1412bc4924c4b51d796e09391f2baeb-1.jpg","url":"https://tv.cctv.com/2011/07/23/VIDEA0BVwHIUe77gElK1TNFS110723.shtml","catalog":"","allow_share":"1","allow_praise":"1","allow_comment":"1","channel_id":"CHAL1450952056131267","topic_id":"TOPC1451528971114112","primary_page_id":"PAGE4y8I53JvSWE8DlRSMlbu160121","desc":"","brief":"","tag":""}}]}
