{"total":16,"videoList":[{"num":1,"video_id":"VIDEIgVxB9pS3ojD4iljjgjR120217","video_title":"[视频]山西院团走市场 剧目叫好又叫座","video_image":"https://p4.img.cctvpic.com/fmspic/2012/02/17/8144829e19944389992273f619b010af-1.jpg","guid":"8144829e19944389992273f619b010af","video_length":"00:03:29","video_tag":"","video_url":"https://tv.cctv.com/2012/02/17/VIDEIgVxB9pS3ojD4iljjgjR120217.shtml","page_id":"PAGE4y8I53JvSWE8DlRSMlbu160121","edit_mode":"1","brief":"","pub_date":"2012-02-17 19:13:50","news_hl_tag":"","video_detail":{"id":"VIDEIgVxB9pS3ojD4iljjgjR120217","guid":"8144829e19944389992273f619b010af","title":"[视频]山西院团走市场 剧目叫好又叫座","source":"央视网","pubtime":"2012-02-17 19:13:50","content":"","logo":"https://p4.img.cctvpic.com/fmspic/2012/02/17/8144829e19944389992273f619b010af-1.jpg","url":"https://tv.cctv.com/2012/02/17/VIDEIgVxB9pS3ojD4iljjgjR120217.shtml","catalog":"","allow_share":"1","allow_praise":"1","allow_comment":"1","channel_id":"CHAL1450952056131267","topic_id":"TOPC1451528971114112","primary_page_id":"PAGE4y8I53JvSWE8DlRSMlbu160121","desc":"","brief":"","tag":""}},{"num":2,"video_id":"VIDEEgNStF4j4WspA0NDK6Wg120217","video_title":"[视频]贾庆林分别会见日本日中友好七团体负责人和欧盟委员会前主席","video_image":"https://p4.img.cctvpic.com/fmspic/2012/02/17/969e1a6daed74b179d879b6408f74aec-1.jpg","guid":"969e1a6daed74b179d879b6408f74aec","video_length":"00:02:12","video_tag":"","video_url":"https://tv.cctv.com/2012/02/17/VIDEEgNStF4j4WspA0NDK6Wg120217.shtml","page_id":"PAGE4y8I53JvSWE8DlRSMlbu160121","edit_mode":"1","brief":"","pub_date":"2012-02-17 19:14:37","news_hl_tag":"","video_detail":{"id":"VIDEEgNStF4j4WspA0NDK6Wg120217","guid":"969e1a6daed74b179d879b6408f74aec","title":"[视频]贾庆林分别会见日本日中友好七团体负责人和欧盟委员会前主席","source":"央视网","pubtime":"2012-02-17 19:14:37","content":"","logo":"https://p4.img.cctvpic.com/fmspic/2012/02/17/969e1a6daed74b179d879b6408f74aec-1.jpg","url":"https://tv.cctv.com/2012/02/17/VIDEEgNStF4j4WspA0NDK6Wg120217.shtml","catalog":"","allow_share":"1","allow_praise":"1","allow_comment":"1","channel_id":"CHAL1450952056131267","topic_id":"TOPC1451528971114112","primary_page_id":"PAGE4y8I53JvSWE8DlRSMlbu160121","desc":"","brief":"","tag":""}},{"num":3,"video_id":"VIDEyhgPVhzA2nI2utDOeLfL120217","video_title":"[视频]习近平参观考察美国农场","video_image":"https://p4.img.cctvpic.com/fmspic/2012/02/17/43b43a9d5f954f2a83e5bd0556ca47fb-1.jpg","guid":"43b43a9d5f954f2a83e5bd0556ca47fb","video_length":"00:01:17","video_tag":"","video_url":"https://tv.cctv.com/2012/02/17/VIDEyhgPVhzA2nI2utDOeLfL120217.shtml","page_id":"PAGE4y8I53JvSWE8DlRSMlbu160121","edit_mode":"1","brief":"","pub_date":"2012-02-17 19:15:22","news_hl_tag":"","video_detail":{"id":"VIDEyhgPVhzA2nI2utDOeLfL120217","guid":"43b43a9d5f954f2a83e5bd0556ca47fb","title":"[视频]习近平参观考察美国农场","source":"央视网","pubtime":"2012-02-17 19:15:22","content":"","logo":"https://p4.img.cctvpic.com/fmspic/2012/02/17/43b43a9d5f954f2a83e5bd0556ca47fb-1.jpg","url":"https://tv.cctv.com/2012/02/17/VIDEyhgPVhzA2nI2utDOeLfL120217.shtml","catalog":"","allow_share":"1","allow_praise":"1","allow_comment":"1","channel_id":"CHAL1450952056131267","topic_id":"TOPC1451528971114112","primary_page_id":"PAGE4y8I53JvSWE8DlRSMlbu160121","desc":"","brief":"","tag":""}},{"num":4,"video_id":"VIDE5FyH8ACWih4rE47heQa3120217","video_title":"[视频]习近平参观考察中海运洛杉矶码头","video_image":"https://p2.img.cctvpic.com/fmspic/2012/02/17/6776ea10f98345d7b6b126d0872a138c-1.jpg","guid":"6776ea10f98345d7b6b126d0872a138c","video_length":"00:01:10","video_tag":"","video_url":"https://tv.cctv.com/2012/02/17/VIDE5FyH8ACWih4rE47heQa3120217.shtml","page_id":"PAGE4y8I53JvSWE8DlRSMlbu160121","edit_mode":"1","brief":"","pub_date":"2012-02-17 19:17:53","news_hl_tag":"","video_detail":{"id":"VIDE5FyH8ACWih4rE47heQa3120217","guid":"6776ea10f98345d7b6b126d0872a138c","title":"[视频]习近平参观考察中海运洛杉矶码头","source":"央视网","pubtime":"2012-02-17 19:17:53","content":"","logo":"https://p2.img.cctvpic.com/fmspic/2012/02/17/6776ea10f98345d7b6b126d0872a138c-1.jpg","url":"https://tv.cctv.com/2012/02/17/VIDE5FyH8ACWih4rE47heQa3120217.shtml","catalog":"","allow_share":"1","allow_praise":"1","allow_comment":"1","channel_id":"CHAL1450952056131267","topic_id":"TOPC1451528971114112","primary_page_id":"PAGE4y8I53JvSWE8DlRSMlbu160121","desc":"","brief":"","tag":""}},{"num":5,"video_id":"VIDEeo1jbsBCeyrRqe4PCYB3120217","video_title":"[视频]李克强强调 把握宏观政策实现稳中求进 深化财税改革激发经济活力","video_image":"https://p1.img.cctvpic.com/fmspic/2012/02/17/ed4a5371757549868033823829814d91-1.jpg","guid":"ed4a5371757549868033823829814d91","video_length":"00:03:08","video_tag":"","video_url":"https://tv.cctv.com/2012/02/17/VIDEeo1jbsBCeyrRqe4PCYB3120217.shtml","page_id":"PAGE4y8I53JvSWE8DlRSMlbu160121","edit_mode":"1","brief":"","pub_date":"2012-02-17 19:24:47","news_hl_tag":"","video_detail":{"id":"VIDEeo1jbsBCeyrRqe4PCYB3120217","guid":"ed4a5371757549868033823829814d91","title":"[视频]李克强强调 把握宏观政策实现稳中求进 深化财税改革激发经济活力","source":"央视网","pubtime":"2012-02-17 19:24:47","content":"","logo":"https://p1.img.cctvpic.com/fmspic/2012/02/17/ed4a5371757549868033823829814d91-1.jpg","url":"https://tv.cctv.com/2012/02/17/VIDEeo1jbsBCeyrRqe4PCYB3120217.shtml","catalog":"","allow_share":"1","allow_praise":"1","allow_comment":"1","channel_id":"CHAL1450952056131267","topic_id":"TOPC1451528971114112","primary_page_id":"PAGE4y8I53JvSWE8DlRSMlbu160121","desc":"","brief":"","tag":""}},{"num":6,"video_id":"VIDEOyLPbKgo2HKxL0cKxiac120217","video_title":"[视频]商务部：1月份我国利用外资出现双降","video_image":"https://p4.img.cctvpic.com/fmspic/2012/02/17/c6ab82e093644ca09bdab2d0437bc23b-1.jpg","guid":"c6ab82e093644ca09bdab2d0437bc23b","video_length":"00:00:49","video_tag":"","video_url":"https://tv.cctv.com/2012/02/17/VIDEOyLPbKgo2HKxL0cKxiac120217.shtml","page_id":"PAGE4y8I53JvSWE8DlRSMlbu160121","edit_mode":"1","brief":"","pub_date":"2012-02-17 19:26:30","news_hl_tag":"","video_detail":{"id":"VIDEOyLPbKgo2HKxL0cKxiac120217","guid":"c6ab82e093644ca09bdab2d0437bc23b","title":"[视频]商务部：1月份我国利用外资出现双降","source":"央视网","pubtime":"2012-02-17 19:26:30","content":"","logo":"https://p4.img.cctvpic.com/fmspic/2012/02/17/c6ab82e093644ca09bdab2d0437bc23b-1.jpg","url":"https://tv.cctv.com/2012/02/17/VIDEOyLPbKgo2HKxL0cKxiac120217.shtml","catalog":"","allow_share":"1","allow_praise":"1","allow_comment":"1","channel_id":"CHAL1450952056131267","topic_id":"TOPC1451528971114112","primary_page_id":"PAGE4y8I53JvSWE8DlRSMlbu160121","desc":"","brief":"","tag":""}},{"num":7,"video_id":"VIDEik3PPpt5GKPQWp2YFhoe120217","video_title":"[视频]银监会促中小银行服务小微企业","video_image":"https://p4.img.cctvpic.com/fmspic/2012/02/17/dc8f7b1268bd48a188b726f478f66f7d-1.jpg","guid":"dc8f7b1268bd48a188b726f478f66f7d","video_length":"00:00:53","video_tag":"","video_url":"https://tv.cctv.com/2012/02/17/VIDEik3PPpt5GKPQWp2YFhoe120217.shtml","page_id":"PAGE4y8I53JvSWE8DlRSMlbu160121","edit_mode":"1","brief":"","pub_date":"2012-02-17 19:27:31","news_hl_tag":"","video_detail":{"id":"VIDEik3PPpt5GKPQWp2YFhoe120217","guid":"dc8f7b1268bd48a188b726f478f66f7d","title":"[视频]银监会促中小银行服务小微企业","source":"央视网","pubtime":"2012-02-17 19:27:31","content":"","logo":"https://p4.img.cctvpic.com/fmspic/2012/02/17/dc8f7b1268bd48a188b726f478f66f7d-1.jpg","url":"https://tv.cctv.com/2012/02/17/VIDEik3PPpt5GKPQWp2YFhoe120217.shtml","catalog":"","allow_share":"1","allow_praise":"1","allow_comment":"1","channel_id":"CHAL1450952056131267","topic_id":"TOPC1451528971114112","primary_page_id":"PAGE4y8I53JvSWE8DlRSMlbu160121","desc":"","brief":"","tag":""}},{"num":8,"video_id":"VIDEGnnVTou4UU66vrYMqUCV120217","video_title":"[视频]宁夏率先基本实现广电“户户通”","video_image":"https://p5.img.cctvpic.com/fmspic/2012/02/17/7f76322f68174876ad4bf2c71d238386-1.jpg","guid":"7f76322f68174876ad4bf2c71d238386","video_length":"00:01:19","video_tag":"","video_url":"https://tv.cctv.com/2012/02/17/VIDEGnnVTou4UU66vrYMqUCV120217.shtml","page_id":"PAGE4y8I53JvSWE8DlRSMlbu160121","edit_mode":"1","brief":"","pub_date":"2012-02-17 19:28:14","news_hl_tag":"","video_detail":{"id":"VIDEGnnVTou4UU66vrYMqUCV120217","guid":"7f76322f68174876ad4bf2c71d238386","title":"[视频]宁夏率先基本实现广电“户户通”","source":"央视网","pubtime":"2012-02-17 19:28:14","content":"","logo":"https://p5.img.cctvpic.com/fmspic/2012/02/17/7f76322f68174876ad4bf2c71d238386-1.jpg","url":"https://tv.cctv.com/2012/02/17/VIDEGnnVTou4UU66vrYMqUCV120217.shtml","catalog":"","allow_share":"1","allow_praise":"1","allow_comment":"1","channel_id":"CHAL1450952056131267","topic_id":"TOPC1451528971114112","primary_page_id":"PAGE4y8I53JvSWE8DlRSMlbu160121","desc":"","brief":"","tag":""}},{"num":9,"video_id":"VIDEy0ace4TfyYKVVwwu5yzq120217","video_title":"[视频]春运期间道路交通事故同比大幅下降","video_image":"https://p1.img.cctvpic.com/fmspic/2012/02/17/17b17296bc154f899ab7119f9bff6272-1.jpg","guid":"17b17296bc154f899ab7119f9bff6272","video_length":"00:00:38","video_tag":"","video_url":"https://tv.cctv.com/2012/02/17/VIDEy0ace4TfyYKVVwwu5yzq120217.shtml","page_id":"PAGE4y8I53JvSWE8DlRSMlbu160121","edit_mode":"1","brief":"","pub_date":"2012-02-17 19:29:17","news_hl_tag":"","video_detail":{"id":"VIDEy0ace4TfyYKVVwwu5yzq120217","guid":"17b17296bc154f899ab7119f9bff6272","title":"[视频]春运期间道路交通事故同比大幅下降","source":"央视网","pubtime":"2012-02-17 19:29:17","content":"","logo":"https://p1.img.cctvpic.com/fmspic/2012/02/17/17b17296bc154f899ab7119f9bff6272-1.jpg","url":"https://tv.cctv.com/2012/02/17/VIDEy0ace4TfyYKVVwwu5yzq120217.shtml","catalog":"","allow_share":"1","allow_praise":"1","allow_comment":"1","channel_id":"CHAL1450952056131267","topic_id":"TOPC1451528971114112","primary_page_id":"PAGE4y8I53JvSWE8DlRSMlbu160121","desc":"","brief":"","tag":""}},{"num":10,"video_id":"VIDEpA6o5heOsafiQuh8Nt7e120217","video_title":"[视频]胡锦涛主席特使周铁农出席土库曼斯坦总统就职仪式","video_image":"https://p4.img.cctvpic.com/fmspic/2012/02/17/a0334c36a380404a8614948c10793ceb-1.jpg","guid":"a0334c36a380404a8614948c10793ceb","video_length":"00:00:20","video_tag":"","video_url":"https://tv.cctv.com/2012/02/17/VIDEpA6o5heOsafiQuh8Nt7e120217.shtml","page_id":"PAGE4y8I53JvSWE8DlRSMlbu160121","edit_mode":"1","brief":"","pub_date":"2012-02-17 19:30:32","news_hl_tag":"","video_detail":{"id":"VIDEpA6o5heOsafiQuh8Nt7e120217","guid":"a0334c36a380404a8614948c10793ceb","title":"[视频]胡锦涛主席特使周铁农出席土库曼斯坦总统就职仪式","source":"央视网","pubtime":"2012-02-17 19:30:32","content":"","logo":"https://p4.img.cctvpic.com/fmspic/2012/02/17/a0334c36a380404a8614948c10793ceb-1.jpg","url":"https://tv.cctv.com/2012/02/17/VIDEpA6o5heOsafiQuh8Nt7e120217.shtml","catalog":"","allow_share":"1","allow_praise":"1","allow_comment":"1","channel_id":"CHAL1450952056131267","topic_id":"TOPC1451528971114112","primary_page_id":"PAGE4y8I53JvSWE8DlRSMlbu160121","desc":"","brief":"","tag":""}},{"num":11,"video_id":"VIDErAQguj0YRi2WorLfDAO3120217","video_title":"[视频]国内联播快讯","video_image":"https://p2.img.cctvpic.com/fmspic/2012/02/17/e367c3b9178f4716a961e8849a2a0c4a-1.jpg","guid":"e367c3b9178f4716a961e8849a2a0c4a","video_length":"00:01:19","video_tag":"","video_url":"https://tv.cctv.com/2012/02/17/VIDErAQguj0YRi2WorLfDAO3120217.shtml","page_id":"PAGE4y8I53JvSWE8DlRSMlbu160121","edit_mode":"1","brief":"","pub_date":"2012-02-17 19:30:35","news_hl_tag":"","video_detail":{"id":"VIDErAQguj0YRi2WorLfDAO3120217","guid":"e367c3b9178f4716a961e8849a2a0c4a","title":"[视频]国内联播快讯","source":"央视网","pubtime":"2012-02-17 19:30:35","content":"","logo":"https://p2.img.cctvpic.com/fmspic/2012/02/17/e367c3b9178f4716a961e8849a2a0c4a-1.jpg","url":"https://tv.cctv.com/2012/02/17/VIDErAQguj0YRi2WorLfDAO3120217.shtml","catalog":"","allow_share":"1","allow_praise":"1","allow_comment":"1","channel_id":"CHAL1450952056131267","topic_id":"TOPC1451528971114112","primary_page_id":"PAGE4y8I53JvSWE8DlRSMlbu160121","desc":"","brief":"","tag":""}},{"num":12,"video_id":"VIDEJGViBjr3iMX7Z0gHH5S6120217","video_title":"[视频]联大通过有关叙利亚问题决议","video_image":"https://p2.img.cctvpic.com/fmspic/2012/02/17/b65fca03e7634fce865092ad436477dc-1.jpg","guid":"b65fca03e7634fce865092ad436477dc","video_length":"00:01:17","video_tag":"","video_url":"https://tv.cctv.com/2012/02/17/VIDEJGViBjr3iMX7Z0gHH5S6120217.shtml","page_id":"PAGE4y8I53JvSWE8DlRSMlbu160121","edit_mode":"1","brief":"","pub_date":"2012-02-17 19:31:16","news_hl_tag":"","video_detail":{"id":"VIDEJGViBjr3iMX7Z0gHH5S6120217","guid":"b65fca03e7634fce865092ad436477dc","title":"[视频]联大通过有关叙利亚问题决议","source":"央视网","pubtime":"2012-02-17 19:31:16","content":"","logo":"https://p2.img.cctvpic.com/fmspic/2012/02/17/b65fca03e7634fce865092ad436477dc-1.jpg","url":"https://tv.cctv.com/2012/02/17/VIDEJGViBjr3iMX7Z0gHH5S6120217.shtml","catalog":"","allow_share":"1","allow_praise":"1","allow_comment":"1","channel_id":"CHAL1450952056131267","topic_id":"TOPC1451528971114112","primary_page_id":"PAGE4y8I53JvSWE8DlRSMlbu160121","desc":"","brief":"","tag":""}},{"num":13,"video_id":"VIDEXgJpdWKFV0UfHF7DDuP5120217","video_title":"[视频]德国总统武尔夫今天宣布辞职","video_image":"https://p4.img.cctvpic.com/fmspic/2012/02/17/ecaff9de2ec04390be0dfc8119b8c60e-1.jpg","guid":"ecaff9de2ec04390be0dfc8119b8c60e","video_length":"00:00:31","video_tag":"","video_url":"https://tv.cctv.com/2012/02/17/VIDEXgJpdWKFV0UfHF7DDuP5120217.shtml","page_id":"PAGE4y8I53JvSWE8DlRSMlbu160121","edit_mode":"1","brief":"","pub_date":"2012-02-17 19:33:03","news_hl_tag":"","video_detail":{"id":"VIDEXgJpdWKFV0UfHF7DDuP5120217","guid":"ecaff9de2ec04390be0dfc8119b8c60e","title":"[视频]德国总统武尔夫今天宣布辞职","source":"央视网","pubtime":"2012-02-17 19:33:03","content":"","logo":"https://p4.img.cctvpic.com/fmspic/2012/02/17/ecaff9de2ec04390be0dfc8119b8c60e-1.jpg","url":"https://tv.cctv.com/2012/02/17/VIDEXgJpdWKFV0UfHF7DDuP5120217.shtml","catalog":"","allow_share":"1","allow_praise":"1","allow_comment":"1","channel_id":"CHAL1450952056131267","topic_id":"TOPC1451528971114112","primary_page_id":"PAGE4y8I53JvSWE8DlRSMlbu160121","desc":"","brief":"","tag":""}},{"num":14,"video_id":"VIDEn7Scu5dUydGvR4fkrbMJ120217","video_title":"[视频]“文化中国·四海同春”圆满落幕","video_image":"https://p4.img.cctvpic.com/fmspic/2012/02/17/590c688f416f4a9d8f3c7882969d08c3-1.jpg","guid":"590c688f416f4a9d8f3c7882969d08c3","video_length":"00:00:27","video_tag":"","video_url":"https://tv.cctv.com/2012/02/17/VIDEn7Scu5dUydGvR4fkrbMJ120217.shtml","page_id":"PAGE4y8I53JvSWE8DlRSMlbu160121","edit_mode":"1","brief":"","pub_date":"2012-02-17 19:33:20","news_hl_tag":"","video_detail":{"id":"VIDEn7Scu5dUydGvR4fkrbMJ120217","guid":"590c688f416f4a9d8f3c7882969d08c3","title":"[视频]“文化中国·四海同春”圆满落幕","source":"央视网","pubtime":"2012-02-17 19:33:20","content":"","logo":"https://p4.img.cctvpic.com/fmspic/2012/02/17/590c688f416f4a9d8f3c7882969d08c3-1.jpg","url":"https://tv.cctv.com/2012/02/17/VIDEn7Scu5dUydGvR4fkrbMJ120217.shtml","catalog":"","allow_share":"1","allow_praise":"1","allow_comment":"1","channel_id":"CHAL1450952056131267","topic_id":"TOPC1451528971114112","primary_page_id":"PAGE4y8I53JvSWE8DlRSMlbu160121","desc":"","brief":"","tag":""}},{"num":15,"video_id":"VIDE3lufPo0wqR1HmI3o0Gp1120217","video_title":"[视频]中方就叙利亚问题进行解释性发言","video_image":"https://p1.img.cctvpic.com/fmspic/2012/02/17/6f53590dd5974272bb959c5aded9bddb-1.jpg","guid":"6f53590dd5974272bb959c5aded9bddb","video_length":"00:01:37","video_tag":"","video_url":"https://tv.cctv.com/2012/02/17/VIDE3lufPo0wqR1HmI3o0Gp1120217.shtml","page_id":"PAGE4y8I53JvSWE8DlRSMlbu160121","edit_mode":"1","brief":"","pub_date":"2012-02-17 19:33:21","news_hl_tag":"","video_detail":{"id":"VIDE3lufPo0wqR1HmI3o0Gp1120217","guid":"6f53590dd5974272bb959c5aded9bddb","title":"[视频]中方就叙利亚问题进行解释性发言","source":"央视网","pubtime":"2012-02-17 19:33:21","content":"","logo":"https://p1.img.cctvpic.com/fmspic/2012/02/17/6f53590dd5974272bb959c5aded9bddb-1.jpg","url":"https://tv.cctv.com/2012/02/17/VIDE3lufPo0wqR1HmI3o0Gp1120217.shtml","catalog":"","allow_share":"1","allow_praise":"1","allow_comment":"1","channel_id":"CHAL1450952056131267","topic_id":"TOPC1451528971114112","primary_page_id":"PAGE4y8I53JvSWE8DlRSMlbu160121","desc":"","brief":"","tag":""}},{"num":16,"video_id":"VIDE1373968079731391","video_title":"[视频]【走基层·最美的中国人】山东梁山：女孩遭抢 路人出手相救","video_image":"https://p1.img.cctvpic.com/fmspic/2012/02/17/6546907f489f4168b028e3863af70a50-1.jpg","guid":"6546907f489f4168b028e3863af70a50","video_length":"00:02:39","video_tag":"","video_url":"https://tv.cctv.com/2012/02/17/VIDE1373968079731391.shtml","page_id":"PAGE4y8I53JvSWE8DlRSMlbu160121","edit_mode":"1","brief":"","pub_date":"2012-02-17 19:45:12","news_hl_tag":"","video_detail":{"id":"VIDE1373968079731391","guid":"6546907f489f4168b028e3863af70a50","title":"[视频]【走基层·最美的中国人】山东梁山：女孩遭抢 路人出手相救","source":"央视网","pubtime":"2012-02-17 19:45:12","content":"","logo":"https://p1.img.cctvpic.com/fmspic/2012/02/17/6546907f489f4168b028e3863af70a50-1.jpg","url":"https://tv.cctv.com/2012/02/17/VIDE1373968079731391.shtml","catalog":"","allow_share":"1","allow_praise":"1","allow_comment":"1","channel_id":"CHAL1450952056131267","topic_id":"TOPC1451528971114112","primary_page_id":"PAGE4y8I53JvSWE8DlRSMlbu160121","desc":"","brief":"","tag":""}}],"serverTime":1761088880082}
